tableutil/__init__.py
tableutil/_metadata.py
tableutil/cell.py
tableutil/constants.py
tableutil/helpers.py
tableutil/row.py
tableutil/table.py
tableutil/table_html.py
tableutil/text_table.py
tableutil/unicode_csv.py
tableutil/old_unittests/__init__.py
tableutil/old_unittests/table_test.py
tableutil/old_unittests/testing_helpers.py
tableutil/resources/__init__.py
tableutil/resources/table_style.css
tableutil-2.4.5.dist-info/LICENSE.txt
tableutil-2.4.5.dist-info/METADATA
tableutil-2.4.5.dist-info/WHEEL
tableutil-2.4.5.dist-info/entry_points.txt
tableutil-2.4.5.dist-info/top_level.txt
tableutil-2.4.5.dist-info/RECORD
