Metadata-Version: 2.1
Name: tableutil
Version: 2.4.5
Summary: A collection of table creation utilities.
Home-page: https://bitbucket.org/daycoder/tableutil.git
Author: Hywel Thomas
Author-email: hywel.thomas@mac.com
License: MIT
Download-URL: https://bitbucket.org/daycoder/tableutil.git/get/2.4.5.tar
Platform: UNKNOWN
Classifier: Development Status :: 3 - Alpha
Classifier: Intended Audience :: Developers
Classifier: License :: OSI Approved :: MIT License
Classifier: Programming Language :: Python :: 2
Classifier: Programming Language :: Python :: 2.7
Classifier: Programming Language :: Python :: 3
Classifier: Programming Language :: Python :: 3.6
Classifier: Topic :: Utilities
License-File: LICENSE.txt
Requires-Dist: pip (>=18.1)
Requires-Dist: future (>=0.16.0)
Requires-Dist: logging-helper (>=1.7.0)
Requires-Dist: conversionutil (>=1.4.2)
Requires-Dist: fdutil (>=1.8.0)
Requires-Dist: attrs (>=16.3.0)
Requires-Dist: dominate (>=2.3.1)
Provides-Extra: test
